LICENSE
MANIFEST.in
README.rst
setup.cfg
setup.py
bin/data-build.py
databuild/__init__.py
databuild/builder.py
databuild/buildfile.py
databuild/compat.py
databuild/facets.py
databuild/functional.py
databuild/loader.py
databuild/operator.py
databuild/settings.py
databuild/utils.py
databuild.egg-info/PKG-INFO
databuild.egg-info/SOURCES.txt
databuild.egg-info/dependency_links.txt
databuild.egg-info/requires.txt
databuild.egg-info/top_level.txt
databuild/adapters/__init__.py
databuild/adapters/base/__init__.py
databuild/adapters/base/exceptions.py
databuild/adapters/base/exporter.py
databuild/adapters/base/importer.py
databuild/adapters/base/models.py
databuild/adapters/locmem/__init__.py
databuild/adapters/locmem/exporter.py
databuild/adapters/locmem/models.py
databuild/adapters/shelved/__init__.py
databuild/adapters/shelved/models.py
databuild/environments/__init__.py
databuild/environments/base.py
databuild/environments/noop.py
databuild/environments/python.py
databuild/functions/__init__.py
databuild/functions/data.py
databuild/operations/__init__.py
databuild/operations/columns.py
databuild/operations/operations.py
databuild/operations/sheets.py
databuild/operations/system.py
databuild/tests/__init__.py
databuild/tests/functions.py
databuild/tests/test_adapters.py
databuild/tests/test_environments.py
databuild/tests/test_exporter.py
databuild/tests/test_functional.py
databuild/tests/test_functions.py
databuild/tests/test_importer.py
databuild/tests/test_operations.py
databuild/tests/test_operator.py
databuild/tests/test_parser.py
databuild/vendor/__init__.py
databuild/vendor/unicodecsv/__init__.py